smarty_py/__init__.py
smarty_py/__main__.py
smarty_py/api/__init__.py
smarty_py/api/candidate.py
smarty_py/resources/__init__.py
smarty_py/resources/source_data.py
smarty_py/utils.py
smarty_py-0.1.5.dist-info/LICENSE
smarty_py-0.1.5.dist-info/WHEEL
smarty_py-0.1.5.dist-info/METADATA
smarty_py-0.1.5.dist-info/RECORD
