Metadata-Version: 2.1
Name: smarty-py
Version: 0.1.5
Summary: A demo instance automation tool.
Author: Elliott Maguire
Author-email: e.maguire@smartrecruiters.com
Requires-Python: >=3.8,<4.0
Classifier: Programming Language :: Python :: 3
Classifier: Programming Language :: Python :: 3.8
Requires-Dist: colorama (>=0.4.3,<0.5.0)
Requires-Dist: names (>=0.3.0,<0.4.0)
Requires-Dist: requests (>=2.22.0,<3.0.0)
